superset_loggers/__init__.py
superset_loggers/logger.py
superset_loggers-0.1.3.dist-info/licenses/LICENSE
superset_loggers-0.1.3.dist-info/METADATA
superset_loggers-0.1.3.dist-info/WHEEL
superset_loggers-0.1.3.dist-info/top_level.txt
superset_loggers-0.1.3.dist-info/RECORD
