Metadata-Version: 2.4
Name: superset-loggers
Version: 0.1.3
Summary: Custom logger package
Author-email: Vitaly Kargin <super_set@mail.ru>
License: MIT
Classifier: Programming Language :: Python :: 3
Classifier: License :: OSI Approved :: MIT License
Classifier: Operating System :: OS Independent
Requires-Python: >=3.7
License-File: LICENSE
Dynamic: license-file
